OCyara-1.0.1.dist-info/DESCRIPTION.rst
OCyara-1.0.1.dist-info/METADATA
OCyara-1.0.1.dist-info/RECORD
OCyara-1.0.1.dist-info/WHEEL
OCyara-1.0.1.dist-info/metadata.json
OCyara-1.0.1.dist-info/top_level.txt
ocyara/__init__.py
ocyara/ocyara.py
