Metadata-Version: 2.0
Name: OCyara
Version: 1.0.1
Summary: A Yara rule engine that scans images for matches using Optical Character Recognition (OCR). See the Github page for more information about the Cython, Tesseract, and Leptonica prerequsites.
Home-page: https://github.com/bandrel/OCyara
Author: Bandrel & ryman1
Author-email: example@example.com
License: GPL v3
Platform: UNKNOWN
Requires-Dist: Cython (>=0.25.2)
Requires-Dist: Pillow (>=4.0.0)
Requires-Dist: colorlog
Requires-Dist: tesserocr (>=2.1.3)
Requires-Dist: tqdm
Requires-Dist: yara-python (>=3.5.0)
